deep_semantic_search/__init__.py
deep_semantic_search/deep_image_search.py
deep_semantic_search/deep_text_search.py
deep_semantic_search/rag.py
deep_semantic_search-0.1.1.dist-info/METADATA
deep_semantic_search-0.1.1.dist-info/WHEEL
deep_semantic_search-0.1.1.dist-info/top_level.txt
deep_semantic_search-0.1.1.dist-info/RECORD
