Metadata-Version: 2.4
Name: deep-semantic-search
Version: 0.1.1
Summary: A library for embedding, indexing, and applying semantic search for text and image data
Home-page: https://github.com/Harduex/deep-semantic-search
Author: Harduex
Author-email: Harduex <simeon.simka@gmail.com>
License-Expression: MIT
Project-URL: Homepage, https://github.com/Harduex/deep-semantic-search
Project-URL: Bug Tracker, https://github.com/Harduex/deep-semantic-search/issues
Classifier: Programming Language :: Python :: 3
Classifier: Operating System :: OS Independent
Classifier: Topic :: Scientific/Engineering :: Artificial Intelligence
Classifier: Topic :: Text Processing :: Indexing
Requires-Python: >=3.8
Requires-Dist: sentence-transformers>=2.7.0
Requires-Dist: torch>=2.0.0
Requires-Dist: transformers>=4.30.0
Requires-Dist: faiss-cpu>=1.8.0
Requires-Dist: pandas>=2.0.0
Requires-Dist: numpy>=1.22.0
Requires-Dist: matplotlib>=3.5.0
Requires-Dist: tqdm>=4.60.0
Requires-Dist: beautifulsoup4>=4.9.0
Requires-Dist: kmeans-pytorch>=0.3
Requires-Dist: langchain>=0.1.0
Requires-Dist: langchain-community>=0.0.1
Requires-Dist: pillow>=10.0.0
Dynamic: author
Dynamic: home-page
Dynamic: requires-python
